posextract/__init__.py
posextract/adj_noun_pairs.py
posextract/download_language_model.py
posextract/grammatical_triples.py
posextract/rules.py
posextract/subj_verb_pairs.py
posextract/traversal.py
posextract/triple_extraction.py
posextract/util.py
posextract/verb_phrase.py
posextract-1.2.3.dist-info/LICENSE
posextract-1.2.3.dist-info/METADATA
posextract-1.2.3.dist-info/WHEEL
posextract-1.2.3.dist-info/top_level.txt
posextract-1.2.3.dist-info/RECORD
