Metadata-Version: 2.1
Name: posextract
Version: 1.2.3
Summary: Grammatical information extraction methods designed for the analysis of historical and contemporary textual corpora.
Author-email: Steph Buongiorno <steph.buon@gmail.com>, Alexander Cerpa <acerpa@smu.edu>
License: MIT License
Project-URL: homepage, https://github.com/stephbuon/posextract
Project-URL: repository, https://github.com/stephbuon/posextract
Project-URL: documentation, https://github.com/stephbuon/posextract
Keywords: triples,svo,action,agency
Classifier: License :: OSI Approved :: MIT License
Classifier: Programming Language :: Python
Classifier: Programming Language :: Python :: 3
Requires-Python: >=3.6
License-File: LICENSE
Requires-Dist: spacy
Requires-Dist: pandas
Requires-Dist: tomli ; python_version < "3.11"
Provides-Extra: dev
Requires-Dist: pip-tools ; extra == 'dev'
Requires-Dist: pytest ; extra == 'dev'
